should_color/__init__.py
should_color/_version.py
should_color/py.typed
should_color-0.2.2.dist-info/METADATA
should_color-0.2.2.dist-info/WHEEL
should_color-0.2.2.dist-info/licenses/LICENSE-APACHE.txt
should_color-0.2.2.dist-info/licenses/LICENSE-MIT.txt
should_color-0.2.2.dist-info/RECORD
