Metadata-Version: 2.4
Name: should-color
Version: 0.2.2
Summary: Determine if terminal output should be colored, respecting environment variables
Project-URL: Source, https://github.com/Techcable/should-color.py
Author: Techcable
License-Expression: MIT OR Apache-2.0
License-File: LICENSE-APACHE.txt
License-File: LICENSE-MIT.txt
Keywords: ansi,clicolor,color,no-color,terminal
Classifier: Development Status :: 3 - Alpha
Classifier: Environment :: Console
Classifier: Intended Audience :: Developers
Classifier: Operating System :: Microsoft :: Windows
Classifier: Operating System :: Unix
Classifier: Programming Language :: Python :: 3
Classifier: Topic :: Terminals
Classifier: Topic :: Utilities
Classifier: Typing :: Typed
Requires-Python: >=3.8
Provides-Extra: colorama
Requires-Dist: colorama>=0.4.6; (sys_platform == 'win32' or sys_platform == 'cygwin') and extra == 'colorama'
